pyaxehelper/__init__.py
pyaxehelper/pyaxehelper.py
pyaxehelper-1.2.0.dist-info/LICENSE
pyaxehelper-1.2.0.dist-info/METADATA
pyaxehelper-1.2.0.dist-info/WHEEL
pyaxehelper-1.2.0.dist-info/top_level.txt
pyaxehelper-1.2.0.dist-info/RECORD
