Metadata-Version: 2.1
Name: pyaxehelper
Version: 1.2.0
Summary: UNKNOWN
Home-page: https://github.com/bkornpob/kbastroutils
Author: Kornpob Bhirombhakdi
Author-email: kbhirombhakdi@stsci.edu
License: UNKNOWN
Platform: UNKNOWN
Classifier: Programming Language :: Python :: 3
Classifier: License :: OSI Approved :: MIT License
Classifier: Operating System :: OS Independent
Requires-Python: >=3.6
